{
    "limit": 10,
    "min_ts": 1366730441.223254,
    "returned": 5,
    "seconds": 0.02254199981689453,
    "spell_list": [
        {
            "alternate_advancement": 1,
            "aoe_radius_meters": 0.0,
            "beneficial": 1,
            "cast_secs_hundredths": 0,
            "chardiff": 0,
            "cost": {
                "concentration": 0,
                "health": 0,
                "per_tick": {
                    "health": 0,
                    "power": 0,
                    "savagery": 0
                },
                "power": 0,
                "savagery": 0
            },
            "crc": 1570068116,
            "deity": 0,
            "description": "Increases the damage overtime component of Quick Strike and its upgrades.",
            "description_pvp": "Increases the damage overtime component of Quick Strike and its upgrades.",
            "duration": {
                "does_not_expire": 0,
                "max_sec_tenths": 0,
                "min_sec_tenths": 0
            },
            "effect_list": [
                {
                    "description": "Increases overtime damage by 21%",
                    "indentation": 0
                }
            ],
            "given_by": "alternateadvancement",
            "icon": {
                "backdrop": 315,
                "icon_heroic_op": -1,
                "id": 338
            },
            "id": 3746565649,
            "last_update": 1366730633.814113,
            "level": 0,
            "max_targets": 0,
            "name": "Enhance: Quick Strike",
            "name_lower": "enhance: quick strike",
            "recast_secs": 0.0,
            "recovery_secs_tenths": 0,
            "spellbook": 4,
            "tier": 3,
            "tier_name": "Apprentice",
            "ts": 1366730633.814113,
            "type": "pcinnates",
            "typeid": 4,
            "version": 1
        },
        {
            "alternate_advancement": 1,
            "aoe_radius_meters": 0.0,
            "beneficial": 1,
            "cast_secs_hundredths": 0,
            "chardiff": 0,
            "cost": {
                "concentration": 0,
                "health": 0,
                "per_tick": {
                    "health": 0,
                    "power": 0,
                    "savagery": 0
                },
                "power": 0,
                "savagery": 0
            },
            "crc": 1570068116,
            "deity": 0,
            "description": "Increases the damage overtime component of Quick Strike and its upgrades.",
            "description_pvp": "Increases the damage overtime component of Quick Strike and its upgrades.",
            "duration": {
                "does_not_expire": 0,
                "max_sec_tenths": 0,
                "min_sec_tenths": 0
            },
            "effect_list": [
                {
                    "description": "Increases overtime damage by 14%",
                    "indentation": 0
                }
            ],
            "given_by": "alternateadvancement",
            "icon": {
                "backdrop": 315,
                "icon_heroic_op": -1,
                "id": 338
            },
            "id": 1113583463,
            "last_update": 1366730623.978641,
            "level": 0,
            "max_targets": 0,
            "name": "Enhance: Quick Strike",
            "name_lower": "enhance: quick strike",
            "recast_secs": 0.0,
            "recovery_secs_tenths": 0,
            "spellbook": 4,
            "tier": 2,
            "tier_name": "Apprentice",
            "ts": 1366730623.978641,
            "type": "pcinnates",
            "typeid": 4,
            "version": 1
        },
        {
            "alternate_advancement": 1,
            "aoe_radius_meters": 0.0,
            "beneficial": 1,
            "cast_secs_hundredths": 0,
            "chardiff": 0,
            "cost": {
                "concentration": 0,
                "health": 0,
                "per_tick": {
                    "health": 0,
                    "power": 0,
                    "savagery": 0
                },
                "power": 0,
                "savagery": 0
            },
            "crc": 1570068116,
            "deity": 0,
            "description": "Increases the damage overtime component of Quick Strike and its upgrades.",
            "description_pvp": "Increases the damage overtime component of Quick Strike and its upgrades.",
            "duration": {
                "does_not_expire": 0,
                "max_sec_tenths": 0,
                "min_sec_tenths": 0
            },
            "effect_list": [
                {
                    "description": "Increases overtime damage by 7%",
                    "indentation": 0
                }
            ],
            "given_by": "alternateadvancement",
            "icon": {
                "backdrop": 315,
                "icon_heroic_op": -1,
                "id": 338
            },
            "id": 1044302524,
            "last_update": 1366730455.412121,
            "level": 0,
            "max_targets": 0,
            "name": "Enhance: Quick Strike",
            "name_lower": "enhance: quick strike",
            "recast_secs": 0.0,
            "recovery_secs_tenths": 0,
            "spellbook": 4,
            "tier": 1,
            "tier_name": "Apprentice",
            "ts": 1366730455.412121,
            "type": "pcinnates",
            "typeid": 4,
            "version": 1
        },
        {
            "alternate_advancement": 1,
            "aoe_radius_meters": 0.0,
            "beneficial": 1,
            "cast_secs_hundredths": 0,
            "chardiff": 0,
            "cost": {
                "concentration": 0,
                "health": 0,
                "per_tick": {
                    "health": 0,
                    "power": 0,
                    "savagery": 0
                },
                "power": 0,
                "savagery": 0
            },
            "crc": 1570068116,
            "deity": 0,
            "description": "Increases the damage overtime component of Quick Strike and its upgrades.",
            "description_pvp": "Increases the damage overtime component of Quick Strike and its upgrades.",
            "duration": {
                "does_not_expire": 0,
                "max_sec_tenths": 0,
                "min_sec_tenths": 0
            },
            "effect_list": [
                {
                    "description": "Increases overtime damage by 28%",
                    "indentation": 0
                }
            ],
            "given_by": "alternateadvancement",
            "icon": {
                "backdrop": 315,
                "icon_heroic_op": -1,
                "id": 338
            },
            "id": 3130893521,
            "last_update": 1366730442.966552,
            "level": 0,
            "max_targets": 0,
            "name": "Enhance: Quick Strike",
            "name_lower": "enhance: quick strike",
            "recast_secs": 0.0,
            "recovery_secs_tenths": 0,
            "spellbook": 4,
            "tier": 4,
            "tier_name": "Journeyman",
            "ts": 1366730442.966552,
            "type": "pcinnates",
            "typeid": 4,
            "version": 1
        },
        {
            "alternate_advancement": 1,
            "aoe_radius_meters": 0.0,
            "beneficial": 1,
            "cast_secs_hundredths": 0,
            "chardiff": 0,
            "cost": {
                "concentration": 0,
                "health": 0,
                "per_tick": {
                    "health": 0,
                    "power": 0,
                    "savagery": 0
                },
                "power": 0,
                "savagery": 0
            },
            "crc": 1570068116,
            "deity": 0,
            "description": "Increases the damage overtime component of Quick Strike and its upgrades.",
            "description_pvp": "Increases the damage overtime component of Quick Strike and its upgrades.",
            "duration": {
                "does_not_expire": 0,
                "max_sec_tenths": 0,
                "min_sec_tenths": 0
            },
            "effect_list": [
                {
                    "description": "Increases overtime damage by 35%",
                    "indentation": 0
                }
            ],
            "given_by": "alternateadvancement",
            "icon": {
                "backdrop": 315,
                "icon_heroic_op": -1,
                "id": 338
            },
            "id": 663897511,
            "last_update": 1366730441.223254,
            "level": 0,
            "max_targets": 0,
            "name": "Enhance: Quick Strike",
            "name_lower": "enhance: quick strike",
            "recast_secs": 0.0,
            "recovery_secs_tenths": 0,
            "spellbook": 4,
            "tier": 5,
            "tier_name": "Adept",
            "ts": 1366730441.223254,
            "type": "pcinnates",
            "typeid": 4,
            "version": 1
        }
    ]
}