{
    "limit": 10,
    "min_ts": 1366730444.868222,
    "returned": 10,
    "seconds": 0.04329490661621094,
    "spell_list": [
        {
            "alternate_advancement": 1,
            "aoe_radius_meters": 0.0,
            "beneficial": 1,
            "cast_secs_hundredths": 80,
            "chardiff": 0,
            "cost": {
                "concentration": 0,
                "health": 0,
                "per_tick": {
                    "health": 0,
                    "power": 0,
                    "savagery": 0
                },
                "power": 0,
                "savagery": 0
            },
            "crc": 2395655045,
            "deity": 0,
            "description": "While a shield is equipped, the next time that the Gladiator successfully blocks/parries/ripostes an attack or an enemy blocks/parries/deflects/ripostes the Gladiator, the Gladiator returns with a counterattack. This effect refreshes every 30 seconds.",
            "description_pvp": "While a shield is equipped, the next time that the Gladiator successfully blocks/parries/ripostes an attack or an enemy blocks/parries/deflects/ripostes the Gladiator, the Gladiator returns with a counterattack. This effect refreshes every 30 seconds.",
            "duration": {
                "does_not_expire": 1,
                "max_sec_tenths": 300,
                "min_sec_tenths": 300
            },
            "effect_list": [
                {
                    "description": "Applies Reversal.  Lasts for 30.0 seconds.",
                    "indentation": 0
                },
                {
                    "description": "When riposted this spell will cast Gladiator's Strike on target's victim.  ",
                    "indentation": 1
                },
                {
                    "description": "Inflicts 7 - 13 melee damage on target",
                    "indentation": 2
                },
                {
                    "description": "Grants a total of 1 trigger of the spell.",
                    "indentation": 2
                },
                {
                    "description": "When parried this spell will cast Gladiator's Strike on target's victim.  ",
                    "indentation": 1
                },
                {
                    "description": "Inflicts 7 - 13 melee damage on target",
                    "indentation": 2
                },
                {
                    "description": "Grants a total of 1 trigger of the spell.",
                    "indentation": 2
                },
                {
                    "description": "When deflected this spell will cast Gladiator's Strike on target's victim.  ",
                    "indentation": 1
                },
                {
                    "description": "Inflicts 7 - 13 melee damage on target",
                    "indentation": 2
                },
                {
                    "description": "Grants a total of 1 trigger of the spell.",
                    "indentation": 2
                },
                {
                    "description": "On a riposte this spell will cast Gladiator's Strike on target's victim.  ",
                    "indentation": 1
                },
                {
                    "description": "Inflicts 7 - 13 melee damage on target",
                    "indentation": 2
                },
                {
                    "description": "Grants a total of 1 trigger of the spell.",
                    "indentation": 2
                },
                {
                    "description": "When blocked this spell will cast Gladiator's Strike on target's victim.  ",
                    "indentation": 1
                },
                {
                    "description": "Inflicts 7 - 13 melee damage on target",
                    "indentation": 2
                },
                {
                    "description": "Grants a total of 1 trigger of the spell.",
                    "indentation": 2
                },
                {
                    "description": "On a parry this spell will cast Gladiator's Strike on target's victim.  ",
                    "indentation": 1
                },
                {
                    "description": "Inflicts 7 - 13 melee damage on target",
                    "indentation": 2
                },
                {
                    "description": "Grants a total of 1 trigger of the spell.",
                    "indentation": 2
                },
                {
                    "description": "If any of the following are true:",
                    "indentation": 0
                },
                {
                    "description": "If shield equipped in Secondary",
                    "indentation": 1
                },
                {
                    "description": "If buckler equipped in Secondary",
                    "indentation": 1
                },
                {
                    "description": "If towershield equipped in Secondary",
                    "indentation": 1
                },
                {
                    "description": "If kiteshield equipped in Secondary",
                    "indentation": 1
                },
                {
                    "description": "If roundshield equipped in Secondary",
                    "indentation": 1
                }
            ],
            "given_by": "alternateadvancement",
            "icon": {
                "backdrop": -1,
                "icon_heroic_op": -1,
                "id": 575
            },
            "id": 1737407352,
            "last_update": 1366730652.161505,
            "level": 0,
            "max_targets": 0,
            "name": "Reversal",
            "name_lower": "reversal",
            "recast_secs": 1.976285,
            "recovery_secs_tenths": 50,
            "spellbook": 1,
            "tier": 1,
            "tier_name": "Apprentice",
            "ts": 1366730652.161505,
            "type": "arts",
            "typeid": 1,
            "version": 1
        },
        {
            "alternate_advancement": 1,
            "aoe_radius_meters": 0.0,
            "beneficial": 1,
            "cast_secs_hundredths": 80,
            "chardiff": 0,
            "cost": {
                "concentration": 0,
                "health": 0,
                "per_tick": {
                    "health": 0,
                    "power": 0,
                    "savagery": 0
                },
                "power": 0,
                "savagery": 0
            },
            "crc": 2395655045,
            "deity": 0,
            "description": "While a shield is equipped, the next time that the Gladiator successfully blocks/parries/ripostes an attack or an enemy blocks/parries/deflects/ripostes the Gladiator, the Gladiator returns with a counterattack. This effect refreshes every 30 seconds.",
            "description_pvp": "While a shield is equipped, the next time that the Gladiator successfully blocks/parries/ripostes an attack or an enemy blocks/parries/deflects/ripostes the Gladiator, the Gladiator returns with a counterattack. This effect refreshes every 30 seconds.",
            "duration": {
                "does_not_expire": 1,
                "max_sec_tenths": 300,
                "min_sec_tenths": 300
            },
            "effect_list": [
                {
                    "description": "Applies Reversal.  Lasts for 30.0 seconds.",
                    "indentation": 0
                },
                {
                    "description": "When riposted this spell will cast Gladiator's Strike on target's victim.  ",
                    "indentation": 1
                },
                {
                    "description": "Inflicts 14 - 24 melee damage on target",
                    "indentation": 2
                },
                {
                    "description": "Grants a total of 1 trigger of the spell.",
                    "indentation": 2
                },
                {
                    "description": "When parried this spell will cast Gladiator's Strike on target's victim.  ",
                    "indentation": 1
                },
                {
                    "description": "Inflicts 14 - 24 melee damage on target",
                    "indentation": 2
                },
                {
                    "description": "Grants a total of 1 trigger of the spell.",
                    "indentation": 2
                },
                {
                    "description": "When deflected this spell will cast Gladiator's Strike on target's victim.  ",
                    "indentation": 1
                },
                {
                    "description": "Inflicts 14 - 24 melee damage on target",
                    "indentation": 2
                },
                {
                    "description": "Grants a total of 1 trigger of the spell.",
                    "indentation": 2
                },
                {
                    "description": "On a riposte this spell will cast Gladiator's Strike on target's victim.  ",
                    "indentation": 1
                },
                {
                    "description": "Inflicts 14 - 24 melee damage on target",
                    "indentation": 2
                },
                {
                    "description": "Grants a total of 1 trigger of the spell.",
                    "indentation": 2
                },
                {
                    "description": "When blocked this spell will cast Gladiator's Strike on target's victim.  ",
                    "indentation": 1
                },
                {
                    "description": "Inflicts 14 - 24 melee damage on target",
                    "indentation": 2
                },
                {
                    "description": "Grants a total of 1 trigger of the spell.",
                    "indentation": 2
                },
                {
                    "description": "On a parry this spell will cast Gladiator's Strike on target's victim.  ",
                    "indentation": 1
                },
                {
                    "description": "Inflicts 14 - 24 melee damage on target",
                    "indentation": 2
                },
                {
                    "description": "Grants a total of 1 trigger of the spell.",
                    "indentation": 2
                },
                {
                    "description": "If any of the following are true:",
                    "indentation": 0
                },
                {
                    "description": "If shield equipped in Secondary",
                    "indentation": 1
                },
                {
                    "description": "If buckler equipped in Secondary",
                    "indentation": 1
                },
                {
                    "description": "If towershield equipped in Secondary",
                    "indentation": 1
                },
                {
                    "description": "If kiteshield equipped in Secondary",
                    "indentation": 1
                },
                {
                    "description": "If roundshield equipped in Secondary",
                    "indentation": 1
                }
            ],
            "given_by": "alternateadvancement",
            "icon": {
                "backdrop": -1,
                "icon_heroic_op": -1,
                "id": 575
            },
            "id": 2310363671,
            "last_update": 1366730638.064494,
            "level": 0,
            "max_targets": 0,
            "name": "Reversal",
            "name_lower": "reversal",
            "recast_secs": 1.976285,
            "recovery_secs_tenths": 50,
            "spellbook": 1,
            "tier": 10,
            "tier_name": "Grandmaster",
            "ts": 1366730638.064494,
            "type": "arts",
            "typeid": 1,
            "version": 1
        },
        {
            "alternate_advancement": 1,
            "aoe_radius_meters": 0.0,
            "beneficial": 1,
            "cast_secs_hundredths": 80,
            "chardiff": 0,
            "cost": {
                "concentration": 0,
                "health": 0,
                "per_tick": {
                    "health": 0,
                    "power": 0,
                    "savagery": 0
                },
                "power": 0,
                "savagery": 0
            },
            "crc": 2395655045,
            "deity": 0,
            "description": "While a shield is equipped, the next time that the Gladiator successfully blocks/parries/ripostes an attack or an enemy blocks/parries/deflects/ripostes the Gladiator, the Gladiator returns with a counterattack. This effect refreshes every 30 seconds.",
            "description_pvp": "While a shield is equipped, the next time that the Gladiator successfully blocks/parries/ripostes an attack or an enemy blocks/parries/deflects/ripostes the Gladiator, the Gladiator returns with a counterattack. This effect refreshes every 30 seconds.",
            "duration": {
                "does_not_expire": 1,
                "max_sec_tenths": 300,
                "min_sec_tenths": 300
            },
            "effect_list": [
                {
                    "description": "Applies Reversal.  Lasts for 30.0 seconds.",
                    "indentation": 0
                },
                {
                    "description": "When riposted this spell will cast Gladiator's Strike on target's victim.  ",
                    "indentation": 1
                },
                {
                    "description": "Inflicts 12 - 20 melee damage on target",
                    "indentation": 2
                },
                {
                    "description": "Grants a total of 1 trigger of the spell.",
                    "indentation": 2
                },
                {
                    "description": "When parried this spell will cast Gladiator's Strike on target's victim.  ",
                    "indentation": 1
                },
                {
                    "description": "Inflicts 12 - 20 melee damage on target",
                    "indentation": 2
                },
                {
                    "description": "Grants a total of 1 trigger of the spell.",
                    "indentation": 2
                },
                {
                    "description": "When deflected this spell will cast Gladiator's Strike on target's victim.  ",
                    "indentation": 1
                },
                {
                    "description": "Inflicts 12 - 20 melee damage on target",
                    "indentation": 2
                },
                {
                    "description": "Grants a total of 1 trigger of the spell.",
                    "indentation": 2
                },
                {
                    "description": "On a riposte this spell will cast Gladiator's Strike on target's victim.  ",
                    "indentation": 1
                },
                {
                    "description": "Inflicts 12 - 20 melee damage on target",
                    "indentation": 2
                },
                {
                    "description": "Grants a total of 1 trigger of the spell.",
                    "indentation": 2
                },
                {
                    "description": "When blocked this spell will cast Gladiator's Strike on target's victim.  ",
                    "indentation": 1
                },
                {
                    "description": "Inflicts 12 - 20 melee damage on target",
                    "indentation": 2
                },
                {
                    "description": "Grants a total of 1 trigger of the spell.",
                    "indentation": 2
                },
                {
                    "description": "On a parry this spell will cast Gladiator's Strike on target's victim.  ",
                    "indentation": 1
                },
                {
                    "description": "Inflicts 12 - 20 melee damage on target",
                    "indentation": 2
                },
                {
                    "description": "Grants a total of 1 trigger of the spell.",
                    "indentation": 2
                },
                {
                    "description": "If any of the following are true:",
                    "indentation": 0
                },
                {
                    "description": "If shield equipped in Secondary",
                    "indentation": 1
                },
                {
                    "description": "If buckler equipped in Secondary",
                    "indentation": 1
                },
                {
                    "description": "If towershield equipped in Secondary",
                    "indentation": 1
                },
                {
                    "description": "If kiteshield equipped in Secondary",
                    "indentation": 1
                },
                {
                    "description": "If roundshield equipped in Secondary",
                    "indentation": 1
                }
            ],
            "given_by": "alternateadvancement",
            "icon": {
                "backdrop": -1,
                "icon_heroic_op": -1,
                "id": 575
            },
            "id": 2672619726,
            "last_update": 1366730630.726882,
            "level": 0,
            "max_targets": 0,
            "name": "Reversal",
            "name_lower": "reversal",
            "recast_secs": 1.976285,
            "recovery_secs_tenths": 50,
            "spellbook": 1,
            "tier": 7,
            "tier_name": "Expert",
            "ts": 1366730630.726882,
            "type": "arts",
            "typeid": 1,
            "version": 1
        },
        {
            "alternate_advancement": 1,
            "aoe_radius_meters": 0.0,
            "beneficial": 1,
            "cast_secs_hundredths": 80,
            "chardiff": 0,
            "cost": {
                "concentration": 0,
                "health": 0,
                "per_tick": {
                    "health": 0,
                    "power": 0,
                    "savagery": 0
                },
                "power": 0,
                "savagery": 0
            },
            "crc": 2395655045,
            "deity": 0,
            "description": "While a shield is equipped, the next time that the Gladiator successfully blocks/parries/ripostes an attack or an enemy blocks/parries/deflects/ripostes the Gladiator, the Gladiator returns with a counterattack. This effect refreshes every 30 seconds.",
            "description_pvp": "While a shield is equipped, the next time that the Gladiator successfully blocks/parries/ripostes an attack or an enemy blocks/parries/deflects/ripostes the Gladiator, the Gladiator returns with a counterattack. This effect refreshes every 30 seconds.",
            "duration": {
                "does_not_expire": 1,
                "max_sec_tenths": 300,
                "min_sec_tenths": 300
            },
            "effect_list": [
                {
                    "description": "Applies Reversal.  Lasts for 30.0 seconds.",
                    "indentation": 0
                },
                {
                    "description": "When riposted this spell will cast Gladiator's Strike on target's victim.  ",
                    "indentation": 1
                },
                {
                    "description": "Inflicts 8 - 14 melee damage on target",
                    "indentation": 2
                },
                {
                    "description": "Grants a total of 1 trigger of the spell.",
                    "indentation": 2
                },
                {
                    "description": "When parried this spell will cast Gladiator's Strike on target's victim.  ",
                    "indentation": 1
                },
                {
                    "description": "Inflicts 8 - 14 melee damage on target",
                    "indentation": 2
                },
                {
                    "description": "Grants a total of 1 trigger of the spell.",
                    "indentation": 2
                },
                {
                    "description": "When deflected this spell will cast Gladiator's Strike on target's victim.  ",
                    "indentation": 1
                },
                {
                    "description": "Inflicts 8 - 14 melee damage on target",
                    "indentation": 2
                },
                {
                    "description": "Grants a total of 1 trigger of the spell.",
                    "indentation": 2
                },
                {
                    "description": "On a riposte this spell will cast Gladiator's Strike on target's victim.  ",
                    "indentation": 1
                },
                {
                    "description": "Inflicts 8 - 14 melee damage on target",
                    "indentation": 2
                },
                {
                    "description": "Grants a total of 1 trigger of the spell.",
                    "indentation": 2
                },
                {
                    "description": "When blocked this spell will cast Gladiator's Strike on target's victim.  ",
                    "indentation": 1
                },
                {
                    "description": "Inflicts 8 - 14 melee damage on target",
                    "indentation": 2
                },
                {
                    "description": "Grants a total of 1 trigger of the spell.",
                    "indentation": 2
                },
                {
                    "description": "On a parry this spell will cast Gladiator's Strike on target's victim.  ",
                    "indentation": 1
                },
                {
                    "description": "Inflicts 8 - 14 melee damage on target",
                    "indentation": 2
                },
                {
                    "description": "Grants a total of 1 trigger of the spell.",
                    "indentation": 2
                },
                {
                    "description": "If any of the following are true:",
                    "indentation": 0
                },
                {
                    "description": "If shield equipped in Secondary",
                    "indentation": 1
                },
                {
                    "description": "If buckler equipped in Secondary",
                    "indentation": 1
                },
                {
                    "description": "If towershield equipped in Secondary",
                    "indentation": 1
                },
                {
                    "description": "If kiteshield equipped in Secondary",
                    "indentation": 1
                },
                {
                    "description": "If roundshield equipped in Secondary",
                    "indentation": 1
                }
            ],
            "given_by": "alternateadvancement",
            "icon": {
                "backdrop": -1,
                "icon_heroic_op": -1,
                "id": 575
            },
            "id": 468688547,
            "last_update": 1366730464.066692,
            "level": 0,
            "max_targets": 0,
            "name": "Reversal",
            "name_lower": "reversal",
            "recast_secs": 1.976285,
            "recovery_secs_tenths": 50,
            "spellbook": 1,
            "tier": 2,
            "tier_name": "Apprentice",
            "ts": 1366730464.066692,
            "type": "arts",
            "typeid": 1,
            "version": 1
        },
        {
            "alternate_advancement": 1,
            "aoe_radius_meters": 0.0,
            "beneficial": 1,
            "cast_secs_hundredths": 80,
            "chardiff": 0,
            "cost": {
                "concentration": 0,
                "health": 0,
                "per_tick": {
                    "health": 0,
                    "power": 0,
                    "savagery": 0
                },
                "power": 0,
                "savagery": 0
            },
            "crc": 2395655045,
            "deity": 0,
            "description": "While a shield is equipped, the next time that the Gladiator successfully blocks/parries/ripostes an attack or an enemy blocks/parries/deflects/ripostes the Gladiator, the Gladiator returns with a counterattack. This effect refreshes every 30 seconds.",
            "description_pvp": "While a shield is equipped, the next time that the Gladiator successfully blocks/parries/ripostes an attack or an enemy blocks/parries/deflects/ripostes the Gladiator, the Gladiator returns with a counterattack. This effect refreshes every 30 seconds.",
            "duration": {
                "does_not_expire": 1,
                "max_sec_tenths": 300,
                "min_sec_tenths": 300
            },
            "effect_list": [
                {
                    "description": "Applies Reversal.  Lasts for 30.0 seconds.",
                    "indentation": 0
                },
                {
                    "description": "When riposted this spell will cast Gladiator's Strike on target's victim.  ",
                    "indentation": 1
                },
                {
                    "description": "Inflicts 8 - 14 melee damage on target",
                    "indentation": 2
                },
                {
                    "description": "Grants a total of 1 trigger of the spell.",
                    "indentation": 2
                },
                {
                    "description": "When parried this spell will cast Gladiator's Strike on target's victim.  ",
                    "indentation": 1
                },
                {
                    "description": "Inflicts 8 - 14 melee damage on target",
                    "indentation": 2
                },
                {
                    "description": "Grants a total of 1 trigger of the spell.",
                    "indentation": 2
                },
                {
                    "description": "When deflected this spell will cast Gladiator's Strike on target's victim.  ",
                    "indentation": 1
                },
                {
                    "description": "Inflicts 8 - 14 melee damage on target",
                    "indentation": 2
                },
                {
                    "description": "Grants a total of 1 trigger of the spell.",
                    "indentation": 2
                },
                {
                    "description": "On a riposte this spell will cast Gladiator's Strike on target's victim.  ",
                    "indentation": 1
                },
                {
                    "description": "Inflicts 8 - 14 melee damage on target",
                    "indentation": 2
                },
                {
                    "description": "Grants a total of 1 trigger of the spell.",
                    "indentation": 2
                },
                {
                    "description": "When blocked this spell will cast Gladiator's Strike on target's victim.  ",
                    "indentation": 1
                },
                {
                    "description": "Inflicts 8 - 14 melee damage on target",
                    "indentation": 2
                },
                {
                    "description": "Grants a total of 1 trigger of the spell.",
                    "indentation": 2
                },
                {
                    "description": "On a parry this spell will cast Gladiator's Strike on target's victim.  ",
                    "indentation": 1
                },
                {
                    "description": "Inflicts 8 - 14 melee damage on target",
                    "indentation": 2
                },
                {
                    "description": "Grants a total of 1 trigger of the spell.",
                    "indentation": 2
                },
                {
                    "description": "If any of the following are true:",
                    "indentation": 0
                },
                {
                    "description": "If shield equipped in Secondary",
                    "indentation": 1
                },
                {
                    "description": "If buckler equipped in Secondary",
                    "indentation": 1
                },
                {
                    "description": "If towershield equipped in Secondary",
                    "indentation": 1
                },
                {
                    "description": "If kiteshield equipped in Secondary",
                    "indentation": 1
                },
                {
                    "description": "If roundshield equipped in Secondary",
                    "indentation": 1
                }
            ],
            "given_by": "alternateadvancement",
            "icon": {
                "backdrop": -1,
                "icon_heroic_op": -1,
                "id": 575
            },
            "id": 2262859733,
            "last_update": 1366730459.046716,
            "level": 0,
            "max_targets": 0,
            "name": "Reversal",
            "name_lower": "reversal",
            "recast_secs": 1.976285,
            "recovery_secs_tenths": 50,
            "spellbook": 1,
            "tier": 3,
            "tier_name": "Apprentice",
            "ts": 1366730459.046716,
            "type": "arts",
            "typeid": 1,
            "version": 1
        },
        {
            "alternate_advancement": 1,
            "aoe_radius_meters": 0.0,
            "beneficial": 1,
            "cast_secs_hundredths": 80,
            "chardiff": 0,
            "cost": {
                "concentration": 0,
                "health": 0,
                "per_tick": {
                    "health": 0,
                    "power": 0,
                    "savagery": 0
                },
                "power": 0,
                "savagery": 0
            },
            "crc": 2395655045,
            "deity": 0,
            "description": "While a shield is equipped, the next time that the Gladiator successfully blocks/parries/ripostes an attack or an enemy blocks/parries/deflects/ripostes the Gladiator, the Gladiator returns with a counterattack. This effect refreshes every 30 seconds.",
            "description_pvp": "While a shield is equipped, the next time that the Gladiator successfully blocks/parries/ripostes an attack or an enemy blocks/parries/deflects/ripostes the Gladiator, the Gladiator returns with a counterattack. This effect refreshes every 30 seconds.",
            "duration": {
                "does_not_expire": 1,
                "max_sec_tenths": 300,
                "min_sec_tenths": 300
            },
            "effect_list": [
                {
                    "description": "Applies Reversal.  Lasts for 30.0 seconds.",
                    "indentation": 0
                },
                {
                    "description": "When riposted this spell will cast Gladiator's Strike on target's victim.  ",
                    "indentation": 1
                },
                {
                    "description": "Inflicts 14 - 23 melee damage on target",
                    "indentation": 2
                },
                {
                    "description": "Grants a total of 1 trigger of the spell.",
                    "indentation": 2
                },
                {
                    "description": "When parried this spell will cast Gladiator's Strike on target's victim.  ",
                    "indentation": 1
                },
                {
                    "description": "Inflicts 14 - 23 melee damage on target",
                    "indentation": 2
                },
                {
                    "description": "Grants a total of 1 trigger of the spell.",
                    "indentation": 2
                },
                {
                    "description": "When deflected this spell will cast Gladiator's Strike on target's victim.  ",
                    "indentation": 1
                },
                {
                    "description": "Inflicts 14 - 23 melee damage on target",
                    "indentation": 2
                },
                {
                    "description": "Grants a total of 1 trigger of the spell.",
                    "indentation": 2
                },
                {
                    "description": "On a riposte this spell will cast Gladiator's Strike on target's victim.  ",
                    "indentation": 1
                },
                {
                    "description": "Inflicts 14 - 23 melee damage on target",
                    "indentation": 2
                },
                {
                    "description": "Grants a total of 1 trigger of the spell.",
                    "indentation": 2
                },
                {
                    "description": "When blocked this spell will cast Gladiator's Strike on target's victim.  ",
                    "indentation": 1
                },
                {
                    "description": "Inflicts 14 - 23 melee damage on target",
                    "indentation": 2
                },
                {
                    "description": "Grants a total of 1 trigger of the spell.",
                    "indentation": 2
                },
                {
                    "description": "On a parry this spell will cast Gladiator's Strike on target's victim.  ",
                    "indentation": 1
                },
                {
                    "description": "Inflicts 14 - 23 melee damage on target",
                    "indentation": 2
                },
                {
                    "description": "Grants a total of 1 trigger of the spell.",
                    "indentation": 2
                },
                {
                    "description": "If any of the following are true:",
                    "indentation": 0
                },
                {
                    "description": "If shield equipped in Secondary",
                    "indentation": 1
                },
                {
                    "description": "If buckler equipped in Secondary",
                    "indentation": 1
                },
                {
                    "description": "If towershield equipped in Secondary",
                    "indentation": 1
                },
                {
                    "description": "If kiteshield equipped in Secondary",
                    "indentation": 1
                },
                {
                    "description": "If roundshield equipped in Secondary",
                    "indentation": 1
                }
            ],
            "given_by": "alternateadvancement",
            "icon": {
                "backdrop": -1,
                "icon_heroic_op": -1,
                "id": 575
            },
            "id": 1423418702,
            "last_update": 1366730456.482841,
            "level": 0,
            "max_targets": 0,
            "name": "Reversal",
            "name_lower": "reversal",
            "recast_secs": 1.976285,
            "recovery_secs_tenths": 50,
            "spellbook": 1,
            "tier": 9,
            "tier_name": "Master",
            "ts": 1366730456.482841,
            "type": "arts",
            "typeid": 1,
            "version": 1
        },
        {
            "alternate_advancement": 1,
            "aoe_radius_meters": 0.0,
            "beneficial": 1,
            "cast_secs_hundredths": 80,
            "chardiff": 0,
            "cost": {
                "concentration": 0,
                "health": 0,
                "per_tick": {
                    "health": 0,
                    "power": 0,
                    "savagery": 0
                },
                "power": 0,
                "savagery": 0
            },
            "crc": 2395655045,
            "deity": 0,
            "description": "While a shield is equipped, the next time that the Gladiator successfully blocks/parries/ripostes an attack or an enemy blocks/parries/deflects/ripostes the Gladiator, the Gladiator returns with a counterattack. This effect refreshes every 30 seconds.",
            "description_pvp": "While a shield is equipped, the next time that the Gladiator successfully blocks/parries/ripostes an attack or an enemy blocks/parries/deflects/ripostes the Gladiator, the Gladiator returns with a counterattack. This effect refreshes every 30 seconds.",
            "duration": {
                "does_not_expire": 1,
                "max_sec_tenths": 300,
                "min_sec_tenths": 300
            },
            "effect_list": [
                {
                    "description": "Applies Reversal.  Lasts for 30.0 seconds.",
                    "indentation": 0
                },
                {
                    "description": "When riposted this spell will cast Gladiator's Strike on target's victim.  ",
                    "indentation": 1
                },
                {
                    "description": "Inflicts 10 - 17 melee damage on target",
                    "indentation": 2
                },
                {
                    "description": "Grants a total of 1 trigger of the spell.",
                    "indentation": 2
                },
                {
                    "description": "When parried this spell will cast Gladiator's Strike on target's victim.  ",
                    "indentation": 1
                },
                {
                    "description": "Inflicts 10 - 17 melee damage on target",
                    "indentation": 2
                },
                {
                    "description": "Grants a total of 1 trigger of the spell.",
                    "indentation": 2
                },
                {
                    "description": "When deflected this spell will cast Gladiator's Strike on target's victim.  ",
                    "indentation": 1
                },
                {
                    "description": "Inflicts 10 - 17 melee damage on target",
                    "indentation": 2
                },
                {
                    "description": "Grants a total of 1 trigger of the spell.",
                    "indentation": 2
                },
                {
                    "description": "On a riposte this spell will cast Gladiator's Strike on target's victim.  ",
                    "indentation": 1
                },
                {
                    "description": "Inflicts 10 - 17 melee damage on target",
                    "indentation": 2
                },
                {
                    "description": "Grants a total of 1 trigger of the spell.",
                    "indentation": 2
                },
                {
                    "description": "When blocked this spell will cast Gladiator's Strike on target's victim.  ",
                    "indentation": 1
                },
                {
                    "description": "Inflicts 10 - 17 melee damage on target",
                    "indentation": 2
                },
                {
                    "description": "Grants a total of 1 trigger of the spell.",
                    "indentation": 2
                },
                {
                    "description": "On a parry this spell will cast Gladiator's Strike on target's victim.  ",
                    "indentation": 1
                },
                {
                    "description": "Inflicts 10 - 17 melee damage on target",
                    "indentation": 2
                },
                {
                    "description": "Grants a total of 1 trigger of the spell.",
                    "indentation": 2
                },
                {
                    "description": "If any of the following are true:",
                    "indentation": 0
                },
                {
                    "description": "If shield equipped in Secondary",
                    "indentation": 1
                },
                {
                    "description": "If buckler equipped in Secondary",
                    "indentation": 1
                },
                {
                    "description": "If towershield equipped in Secondary",
                    "indentation": 1
                },
                {
                    "description": "If kiteshield equipped in Secondary",
                    "indentation": 1
                },
                {
                    "description": "If roundshield equipped in Secondary",
                    "indentation": 1
                }
            ],
            "given_by": "alternateadvancement",
            "icon": {
                "backdrop": -1,
                "icon_heroic_op": -1,
                "id": 575
            },
            "id": 2116170851,
            "last_update": 1366730454.905559,
            "level": 0,
            "max_targets": 0,
            "name": "Reversal",
            "name_lower": "reversal",
            "recast_secs": 1.976285,
            "recovery_secs_tenths": 50,
            "spellbook": 1,
            "tier": 5,
            "tier_name": "Adept",
            "ts": 1366730454.905559,
            "type": "arts",
            "typeid": 1,
            "version": 1
        },
        {
            "alternate_advancement": 1,
            "aoe_radius_meters": 0.0,
            "beneficial": 1,
            "cast_secs_hundredths": 80,
            "chardiff": 0,
            "cost": {
                "concentration": 0,
                "health": 0,
                "per_tick": {
                    "health": 0,
                    "power": 0,
                    "savagery": 0
                },
                "power": 0,
                "savagery": 0
            },
            "crc": 2395655045,
            "deity": 0,
            "description": "While a shield is equipped, the next time that the Gladiator successfully blocks/parries/ripostes an attack or an enemy blocks/parries/deflects/ripostes the Gladiator, the Gladiator returns with a counterattack. This effect refreshes every 30 seconds.",
            "description_pvp": "While a shield is equipped, the next time that the Gladiator successfully blocks/parries/ripostes an attack or an enemy blocks/parries/deflects/ripostes the Gladiator, the Gladiator returns with a counterattack. This effect refreshes every 30 seconds.",
            "duration": {
                "does_not_expire": 1,
                "max_sec_tenths": 300,
                "min_sec_tenths": 300
            },
            "effect_list": [
                {
                    "description": "Applies Reversal.  Lasts for 30.0 seconds.",
                    "indentation": 0
                },
                {
                    "description": "When riposted this spell will cast Gladiator's Strike on target's victim.  ",
                    "indentation": 1
                },
                {
                    "description": "Inflicts 13 - 22 melee damage on target",
                    "indentation": 2
                },
                {
                    "description": "Grants a total of 1 trigger of the spell.",
                    "indentation": 2
                },
                {
                    "description": "When parried this spell will cast Gladiator's Strike on target's victim.  ",
                    "indentation": 1
                },
                {
                    "description": "Inflicts 13 - 22 melee damage on target",
                    "indentation": 2
                },
                {
                    "description": "Grants a total of 1 trigger of the spell.",
                    "indentation": 2
                },
                {
                    "description": "When deflected this spell will cast Gladiator's Strike on target's victim.  ",
                    "indentation": 1
                },
                {
                    "description": "Inflicts 13 - 22 melee damage on target",
                    "indentation": 2
                },
                {
                    "description": "Grants a total of 1 trigger of the spell.",
                    "indentation": 2
                },
                {
                    "description": "On a riposte this spell will cast Gladiator's Strike on target's victim.  ",
                    "indentation": 1
                },
                {
                    "description": "Inflicts 13 - 22 melee damage on target",
                    "indentation": 2
                },
                {
                    "description": "Grants a total of 1 trigger of the spell.",
                    "indentation": 2
                },
                {
                    "description": "When blocked this spell will cast Gladiator's Strike on target's victim.  ",
                    "indentation": 1
                },
                {
                    "description": "Inflicts 13 - 22 melee damage on target",
                    "indentation": 2
                },
                {
                    "description": "Grants a total of 1 trigger of the spell.",
                    "indentation": 2
                },
                {
                    "description": "On a parry this spell will cast Gladiator's Strike on target's victim.  ",
                    "indentation": 1
                },
                {
                    "description": "Inflicts 13 - 22 melee damage on target",
                    "indentation": 2
                },
                {
                    "description": "Grants a total of 1 trigger of the spell.",
                    "indentation": 2
                },
                {
                    "description": "If any of the following are true:",
                    "indentation": 0
                },
                {
                    "description": "If shield equipped in Secondary",
                    "indentation": 1
                },
                {
                    "description": "If buckler equipped in Secondary",
                    "indentation": 1
                },
                {
                    "description": "If towershield equipped in Secondary",
                    "indentation": 1
                },
                {
                    "description": "If kiteshield equipped in Secondary",
                    "indentation": 1
                },
                {
                    "description": "If roundshield equipped in Secondary",
                    "indentation": 1
                }
            ],
            "given_by": "alternateadvancement",
            "icon": {
                "backdrop": -1,
                "icon_heroic_op": -1,
                "id": 575
            },
            "id": 3386393656,
            "last_update": 1366730453.807317,
            "level": 0,
            "max_targets": 0,
            "name": "Reversal",
            "name_lower": "reversal",
            "recast_secs": 1.976285,
            "recovery_secs_tenths": 50,
            "spellbook": 1,
            "tier": 8,
            "tier_name": "Expert",
            "ts": 1366730453.807317,
            "type": "arts",
            "typeid": 1,
            "version": 1
        },
        {
            "alternate_advancement": 1,
            "aoe_radius_meters": 0.0,
            "beneficial": 1,
            "cast_secs_hundredths": 80,
            "chardiff": 0,
            "cost": {
                "concentration": 0,
                "health": 0,
                "per_tick": {
                    "health": 0,
                    "power": 0,
                    "savagery": 0
                },
                "power": 0,
                "savagery": 0
            },
            "crc": 2395655045,
            "deity": 0,
            "description": "While a shield is equipped, the next time that the Gladiator successfully blocks/parries/ripostes an attack or an enemy blocks/parries/deflects/ripostes the Gladiator, the Gladiator returns with a counterattack. This effect refreshes every 30 seconds.",
            "description_pvp": "While a shield is equipped, the next time that the Gladiator successfully blocks/parries/ripostes an attack or an enemy blocks/parries/deflects/ripostes the Gladiator, the Gladiator returns with a counterattack. This effect refreshes every 30 seconds.",
            "duration": {
                "does_not_expire": 1,
                "max_sec_tenths": 300,
                "min_sec_tenths": 300
            },
            "effect_list": [
                {
                    "description": "Applies Reversal.  Lasts for 30.0 seconds.",
                    "indentation": 0
                },
                {
                    "description": "When riposted this spell will cast Gladiator's Strike on target's victim.  ",
                    "indentation": 1
                },
                {
                    "description": "Inflicts 11 - 19 melee damage on target",
                    "indentation": 2
                },
                {
                    "description": "Grants a total of 1 trigger of the spell.",
                    "indentation": 2
                },
                {
                    "description": "When parried this spell will cast Gladiator's Strike on target's victim.  ",
                    "indentation": 1
                },
                {
                    "description": "Inflicts 11 - 19 melee damage on target",
                    "indentation": 2
                },
                {
                    "description": "Grants a total of 1 trigger of the spell.",
                    "indentation": 2
                },
                {
                    "description": "When deflected this spell will cast Gladiator's Strike on target's victim.  ",
                    "indentation": 1
                },
                {
                    "description": "Inflicts 11 - 19 melee damage on target",
                    "indentation": 2
                },
                {
                    "description": "Grants a total of 1 trigger of the spell.",
                    "indentation": 2
                },
                {
                    "description": "On a riposte this spell will cast Gladiator's Strike on target's victim.  ",
                    "indentation": 1
                },
                {
                    "description": "Inflicts 11 - 19 melee damage on target",
                    "indentation": 2
                },
                {
                    "description": "Grants a total of 1 trigger of the spell.",
                    "indentation": 2
                },
                {
                    "description": "When blocked this spell will cast Gladiator's Strike on target's victim.  ",
                    "indentation": 1
                },
                {
                    "description": "Inflicts 11 - 19 melee damage on target",
                    "indentation": 2
                },
                {
                    "description": "Grants a total of 1 trigger of the spell.",
                    "indentation": 2
                },
                {
                    "description": "On a parry this spell will cast Gladiator's Strike on target's victim.  ",
                    "indentation": 1
                },
                {
                    "description": "Inflicts 11 - 19 melee damage on target",
                    "indentation": 2
                },
                {
                    "description": "Grants a total of 1 trigger of the spell.",
                    "indentation": 2
                },
                {
                    "description": "If any of the following are true:",
                    "indentation": 0
                },
                {
                    "description": "If shield equipped in Secondary",
                    "indentation": 1
                },
                {
                    "description": "If buckler equipped in Secondary",
                    "indentation": 1
                },
                {
                    "description": "If towershield equipped in Secondary",
                    "indentation": 1
                },
                {
                    "description": "If kiteshield equipped in Secondary",
                    "indentation": 1
                },
                {
                    "description": "If roundshield equipped in Secondary",
                    "indentation": 1
                }
            ],
            "given_by": "alternateadvancement",
            "icon": {
                "backdrop": -1,
                "icon_heroic_op": -1,
                "id": 575
            },
            "id": 37949880,
            "last_update": 1366730445.599453,
            "level": 0,
            "max_targets": 0,
            "name": "Reversal",
            "name_lower": "reversal",
            "recast_secs": 1.976285,
            "recovery_secs_tenths": 50,
            "spellbook": 1,
            "tier": 6,
            "tier_name": "Adept",
            "ts": 1366730445.599453,
            "type": "arts",
            "typeid": 1,
            "version": 1
        },
        {
            "alternate_advancement": 1,
            "aoe_radius_meters": 0.0,
            "beneficial": 1,
            "cast_secs_hundredths": 80,
            "chardiff": 0,
            "cost": {
                "concentration": 0,
                "health": 0,
                "per_tick": {
                    "health": 0,
                    "power": 0,
                    "savagery": 0
                },
                "power": 0,
                "savagery": 0
            },
            "crc": 2395655045,
            "deity": 0,
            "description": "While a shield is equipped, the next time that the Gladiator successfully blocks/parries/ripostes an attack or an enemy blocks/parries/deflects/ripostes the Gladiator, the Gladiator returns with a counterattack. This effect refreshes every 30 seconds.",
            "description_pvp": "While a shield is equipped, the next time that the Gladiator successfully blocks/parries/ripostes an attack or an enemy blocks/parries/deflects/ripostes the Gladiator, the Gladiator returns with a counterattack. This effect refreshes every 30 seconds.",
            "duration": {
                "does_not_expire": 1,
                "max_sec_tenths": 300,
                "min_sec_tenths": 300
            },
            "effect_list": [
                {
                    "description": "Applies Reversal.  Lasts for 30.0 seconds.",
                    "indentation": 0
                },
                {
                    "description": "When riposted this spell will cast Gladiator's Strike on target's victim.  ",
                    "indentation": 1
                },
                {
                    "description": "Inflicts 9 - 16 melee damage on target",
                    "indentation": 2
                },
                {
                    "description": "Grants a total of 1 trigger of the spell.",
                    "indentation": 2
                },
                {
                    "description": "When parried this spell will cast Gladiator's Strike on target's victim.  ",
                    "indentation": 1
                },
                {
                    "description": "Inflicts 9 - 16 melee damage on target",
                    "indentation": 2
                },
                {
                    "description": "Grants a total of 1 trigger of the spell.",
                    "indentation": 2
                },
                {
                    "description": "When deflected this spell will cast Gladiator's Strike on target's victim.  ",
                    "indentation": 1
                },
                {
                    "description": "Inflicts 9 - 16 melee damage on target",
                    "indentation": 2
                },
                {
                    "description": "Grants a total of 1 trigger of the spell.",
                    "indentation": 2
                },
                {
                    "description": "On a riposte this spell will cast Gladiator's Strike on target's victim.  ",
                    "indentation": 1
                },
                {
                    "description": "Inflicts 9 - 16 melee damage on target",
                    "indentation": 2
                },
                {
                    "description": "Grants a total of 1 trigger of the spell.",
                    "indentation": 2
                },
                {
                    "description": "When blocked this spell will cast Gladiator's Strike on target's victim.  ",
                    "indentation": 1
                },
                {
                    "description": "Inflicts 9 - 16 melee damage on target",
                    "indentation": 2
                },
                {
                    "description": "Grants a total of 1 trigger of the spell.",
                    "indentation": 2
                },
                {
                    "description": "On a parry this spell will cast Gladiator's Strike on target's victim.  ",
                    "indentation": 1
                },
                {
                    "description": "Inflicts 9 - 16 melee damage on target",
                    "indentation": 2
                },
                {
                    "description": "Grants a total of 1 trigger of the spell.",
                    "indentation": 2
                },
                {
                    "description": "If any of the following are true:",
                    "indentation": 0
                },
                {
                    "description": "If shield equipped in Secondary",
                    "indentation": 1
                },
                {
                    "description": "If buckler equipped in Secondary",
                    "indentation": 1
                },
                {
                    "description": "If towershield equipped in Secondary",
                    "indentation": 1
                },
                {
                    "description": "If kiteshield equipped in Secondary",
                    "indentation": 1
                },
                {
                    "description": "If roundshield equipped in Secondary",
                    "indentation": 1
                }
            ],
            "given_by": "alternateadvancement",
            "icon": {
                "backdrop": -1,
                "icon_heroic_op": -1,
                "id": 575
            },
            "id": 3811431701,
            "last_update": 1366730444.868222,
            "level": 0,
            "max_targets": 0,
            "name": "Reversal",
            "name_lower": "reversal",
            "recast_secs": 1.976285,
            "recovery_secs_tenths": 50,
            "spellbook": 1,
            "tier": 4,
            "tier_name": "Journeyman",
            "ts": 1366730444.868222,
            "type": "arts",
            "typeid": 1,
            "version": 1
        }
    ]
}