{
    "limit": 10,
    "min_ts": 1366730440.253307,
    "returned": 5,
    "seconds": 0.020746946334838867,
    "spell_list": [
        {
            "alternate_advancement": 1,
            "aoe_radius_meters": 0.0,
            "beneficial": 1,
            "cast_secs_hundredths": 0,
            "chardiff": 0,
            "cost": {
                "concentration": 0,
                "health": 0,
                "per_tick": {
                    "health": 0,
                    "power": 0,
                    "savagery": 0
                },
                "power": 0,
                "savagery": 0
            },
            "crc": 3644397222,
            "deity": 0,
            "description": "Increases the trigger chance of Involuntary Gift and its upgrades.",
            "description_pvp": "Increases the trigger chance of Involuntary Gift and its upgrades.",
            "duration": {
                "does_not_expire": 0,
                "max_sec_tenths": 0,
                "min_sec_tenths": 0
            },
            "effect_list": [
                {
                    "description": "Increases trigger chance by 8%",
                    "indentation": 0
                }
            ],
            "given_by": "alternateadvancement",
            "icon": {
                "backdrop": 315,
                "icon_heroic_op": -1,
                "id": 180
            },
            "id": 2407839603,
            "last_update": 1366730638.826612,
            "level": 0,
            "max_targets": 0,
            "name": "Enhance: Involuntary Gift",
            "name_lower": "enhance: involuntary gift",
            "recast_secs": 0.0,
            "recovery_secs_tenths": 0,
            "spellbook": 4,
            "tier": 4,
            "tier_name": "Journeyman",
            "ts": 1366730638.826612,
            "type": "pcinnates",
            "typeid": 4,
            "version": 1
        },
        {
            "alternate_advancement": 1,
            "aoe_radius_meters": 0.0,
            "beneficial": 1,
            "cast_secs_hundredths": 0,
            "chardiff": 0,
            "cost": {
                "concentration": 0,
                "health": 0,
                "per_tick": {
                    "health": 0,
                    "power": 0,
                    "savagery": 0
                },
                "power": 0,
                "savagery": 0
            },
            "crc": 3644397222,
            "deity": 0,
            "description": "Increases the trigger chance of Involuntary Gift and its upgrades.",
            "description_pvp": "Increases the trigger chance of Involuntary Gift and its upgrades.",
            "duration": {
                "does_not_expire": 0,
                "max_sec_tenths": 0,
                "min_sec_tenths": 0
            },
            "effect_list": [
                {
                    "description": "Increases trigger chance by 10%",
                    "indentation": 0
                }
            ],
            "given_by": "alternateadvancement",
            "icon": {
                "backdrop": 315,
                "icon_heroic_op": -1,
                "id": 180
            },
            "id": 311121413,
            "last_update": 1366730460.965086,
            "level": 0,
            "max_targets": 0,
            "name": "Enhance: Involuntary Gift",
            "name_lower": "enhance: involuntary gift",
            "recast_secs": 0.0,
            "recovery_secs_tenths": 0,
            "spellbook": 4,
            "tier": 5,
            "tier_name": "Adept",
            "ts": 1366730460.965086,
            "type": "pcinnates",
            "typeid": 4,
            "version": 1
        },
        {
            "alternate_advancement": 1,
            "aoe_radius_meters": 0.0,
            "beneficial": 1,
            "cast_secs_hundredths": 0,
            "chardiff": 0,
            "cost": {
                "concentration": 0,
                "health": 0,
                "per_tick": {
                    "health": 0,
                    "power": 0,
                    "savagery": 0
                },
                "power": 0,
                "savagery": 0
            },
            "crc": 3644397222,
            "deity": 0,
            "description": "Increases the trigger chance of Involuntary Gift and its upgrades.",
            "description_pvp": "Increases the trigger chance of Involuntary Gift and its upgrades.",
            "duration": {
                "does_not_expire": 0,
                "max_sec_tenths": 0,
                "min_sec_tenths": 0
            },
            "effect_list": [
                {
                    "description": "Increases trigger chance by 2%",
                    "indentation": 0
                }
            ],
            "given_by": "alternateadvancement",
            "icon": {
                "backdrop": 315,
                "icon_heroic_op": -1,
                "id": 180
            },
            "id": 187160862,
            "last_update": 1366730457.454907,
            "level": 0,
            "max_targets": 0,
            "name": "Enhance: Involuntary Gift",
            "name_lower": "enhance: involuntary gift",
            "recast_secs": 0.0,
            "recovery_secs_tenths": 0,
            "spellbook": 4,
            "tier": 1,
            "tier_name": "Apprentice",
            "ts": 1366730457.454907,
            "type": "pcinnates",
            "typeid": 4,
            "version": 1
        },
        {
            "alternate_advancement": 1,
            "aoe_radius_meters": 0.0,
            "beneficial": 1,
            "cast_secs_hundredths": 0,
            "chardiff": 0,
            "cost": {
                "concentration": 0,
                "health": 0,
                "per_tick": {
                    "health": 0,
                    "power": 0,
                    "savagery": 0
                },
                "power": 0,
                "savagery": 0
            },
            "crc": 3644397222,
            "deity": 0,
            "description": "Increases the trigger chance of Involuntary Gift and its upgrades.",
            "description_pvp": "Increases the trigger chance of Involuntary Gift and its upgrades.",
            "duration": {
                "does_not_expire": 0,
                "max_sec_tenths": 0,
                "min_sec_tenths": 0
            },
            "effect_list": [
                {
                    "description": "Increases trigger chance by 4%",
                    "indentation": 0
                }
            ],
            "given_by": "alternateadvancement",
            "icon": {
                "backdrop": 315,
                "icon_heroic_op": -1,
                "id": 180
            },
            "id": 2001140933,
            "last_update": 1366730457.228502,
            "level": 0,
            "max_targets": 0,
            "name": "Enhance: Involuntary Gift",
            "name_lower": "enhance: involuntary gift",
            "recast_secs": 0.0,
            "recovery_secs_tenths": 0,
            "spellbook": 4,
            "tier": 2,
            "tier_name": "Apprentice",
            "ts": 1366730457.228502,
            "type": "pcinnates",
            "typeid": 4,
            "version": 1
        },
        {
            "alternate_advancement": 1,
            "aoe_radius_meters": 0.0,
            "beneficial": 1,
            "cast_secs_hundredths": 0,
            "chardiff": 0,
            "cost": {
                "concentration": 0,
                "health": 0,
                "per_tick": {
                    "health": 0,
                    "power": 0,
                    "savagery": 0
                },
                "power": 0,
                "savagery": 0
            },
            "crc": 3644397222,
            "deity": 0,
            "description": "Increases the trigger chance of Involuntary Gift and its upgrades.",
            "description_pvp": "Increases the trigger chance of Involuntary Gift and its upgrades.",
            "duration": {
                "does_not_expire": 0,
                "max_sec_tenths": 0,
                "min_sec_tenths": 0
            },
            "effect_list": [
                {
                    "description": "Increases trigger chance by 6%",
                    "indentation": 0
                }
            ],
            "given_by": "alternateadvancement",
            "icon": {
                "backdrop": 315,
                "icon_heroic_op": -1,
                "id": 180
            },
            "id": 3930660275,
            "last_update": 1366730440.253307,
            "level": 0,
            "max_targets": 0,
            "name": "Enhance: Involuntary Gift",
            "name_lower": "enhance: involuntary gift",
            "recast_secs": 0.0,
            "recovery_secs_tenths": 0,
            "spellbook": 4,
            "tier": 3,
            "tier_name": "Apprentice",
            "ts": 1366730440.253307,
            "type": "pcinnates",
            "typeid": 4,
            "version": 1
        }
    ]
}