{
    "limit": 10,
    "min_ts": 1366730467.589691,
    "returned": 1,
    "seconds": 0.01408696174621582,
    "spell_list": [
        {
            "alternate_advancement": 1,
            "aoe_radius_meters": 5.0,
            "beneficial": 0,
            "cast_secs_hundredths": 80,
            "chardiff": 0,
            "cost": {
                "concentration": 0,
                "health": 0,
                "per_tick": {
                    "health": 0,
                    "power": 0,
                    "savagery": 0
                },
                "power": 0,
                "savagery": 0
            },
            "crc": 3084003135,
            "deity": 0,
            "description": "The bruiser deals large damage in area of effect, increasing hate position.",
            "description_pvp": "The bruiser deals large damage in area of effect, increasing hate position.",
            "duration": {
                "does_not_expire": 0,
                "max_sec_tenths": 0,
                "min_sec_tenths": 0
            },
            "effect_list": [
                {
                    "description": "Inflicts 9 - 11 heat damage on targets in Area of Effect",
                    "indentation": 0
                },
                {
                    "description": "Increases threat priority of targets in Area of Effect by 2 positions",
                    "indentation": 0
                }
            ],
            "given_by": "alternateadvancement",
            "icon": {
                "backdrop": 313,
                "icon_heroic_op": -1,
                "id": 854
            },
            "id": 2924292328,
            "last_update": 1366730467.589691,
            "level": 0,
            "max_targets": 0,
            "name": "Wild Beating",
            "name_lower": "wild beating",
            "recast_secs": 29.64427,
            "recovery_secs_tenths": 50,
            "spellbook": 1,
            "tier": 1,
            "tier_name": "Apprentice",
            "ts": 1366730467.589691,
            "type": "arts",
            "typeid": 1,
            "version": 1
        }
    ]
}